github/com/piotrkowalczuk/charon/pb/rpc/charond/v1/auth_pb2.py
github/com/piotrkowalczuk/charon/pb/rpc/charond/v1/auth_pb2_grpc.py
github/com/piotrkowalczuk/charon/pb/rpc/charond/v1/common_pb2.py
github/com/piotrkowalczuk/charon/pb/rpc/charond/v1/common_pb2_grpc.py
github/com/piotrkowalczuk/charon/pb/rpc/charond/v1/group_pb2.py
github/com/piotrkowalczuk/charon/pb/rpc/charond/v1/group_pb2_grpc.py
github/com/piotrkowalczuk/charon/pb/rpc/charond/v1/permission_pb2.py
github/com/piotrkowalczuk/charon/pb/rpc/charond/v1/permission_pb2_grpc.py
github/com/piotrkowalczuk/charon/pb/rpc/charond/v1/refresh_token_pb2.py
github/com/piotrkowalczuk/charon/pb/rpc/charond/v1/refresh_token_pb2_grpc.py
github/com/piotrkowalczuk/charon/pb/rpc/charond/v1/user_pb2.py
github/com/piotrkowalczuk/charon/pb/rpc/charond/v1/user_pb2_grpc.py
charon_client-0.20.0.dist-info/METADATA
charon_client-0.20.0.dist-info/WHEEL
charon_client-0.20.0.dist-info/top_level.txt
charon_client-0.20.0.dist-info/RECORD
