Metadata-Version: 2.1
Name: charon-client
Version: 0.20.0
Summary: charon service grpc client library
Home-page: http://github.com/piotrkowalczuk/charon
Author: Piotr Kowalczuk
Author-email: p.kowalczuk.priv@gmail.com
License: MIT
Download-URL: https://github.com/piotrkowalczuk/charon/archive/v0.20.0.tar.gz
Keywords: charon,grpc,authentication,authorization,service,client
Platform: UNKNOWN
Requires-Dist: protobuf
Requires-Dist: grpcio
Requires-Dist: protobuf-ntypes
Requires-Dist: protobuf-qtypes
